treillage/__init__.py
treillage/_version.py
treillage/connection_manager.py
treillage/credential.py
treillage/exceptions.py
treillage/ratelimiter.py
treillage/token_manager.py
treillage/treillage.py
treillage/endpoints/__init__.py
treillage/endpoints/document_management.py
treillage/endpoints/list_paginator.py
treillage/endpoints/org_management.py
treillage-0.2.1.dist-info/LICENSE
treillage-0.2.1.dist-info/METADATA
treillage-0.2.1.dist-info/WHEEL
treillage-0.2.1.dist-info/top_level.txt
treillage-0.2.1.dist-info/RECORD
