Metadata-Version: 2.1
Name: treillage
Version: 0.2.1
Summary: Unofficial Wrapper library for the Filevine API
Home-page: https://github.com/W1ndst0rm/Treillage
Author: Levi Jumonville
License: MIT
Platform: UNKNOWN
Classifier: Programming Language :: Python :: 3.8
Classifier: License :: OSI Approved :: MIT License
Classifier: Operating System :: OS Independent
Classifier: Development Status :: 3 - Alpha
Classifier: Framework :: AsyncIO
Classifier: Intended Audience :: Developers
Classifier: Intended Audience :: Information Technology
Classifier: Intended Audience :: Legal Industry
Classifier: Topic :: Software Development :: Libraries :: Python Modules
Classifier: Topic :: Internet
Requires-Python: >=3.8
Requires-Dist: aiohttp (<4,>=3)
Requires-Dist: pandas (<2,>=1)
Requires-Dist: PyYAML (<6,>=5)
Requires-Dist: PyJWT (<3,>=2.5.0)
Requires-Dist: cryptography (<36,>=35)
